[
  {
    "id": "3e6b5fd3-e279-4297-bf64-0bfda199c887",
    "pickup_id": "PICKUP-20251010-0001",
    "company_name": "ABC Electronics",
    "lot_number": "LOT-20251010-001",
    "pickup_date": "2025-01-10",
    "status": "pending",
    "vehicle_number": "UP80GT1234",
    "driver_name": "John Doe",
    "vehicle_charges": 1500,
    "labour_charges": 2000,
    "client_contact": "9876543210",
    "created_at": "2025-10-10T05:12:00.445Z",
    "updated_at": "2025-10-10T05:12:00.445Z"
  },
  {
    "id": "c938372b-55ea-4312-9cae-e039a8b3a7d7",
    "pickup_id": "PICKUP-20251010-0002",
    "company_name": "ABC Electronics",
    "lot_number": "LOT-20251010-001",
    "pickup_date": "2025-01-11",
    "status": "pending",
    "vehicle_number": "UP80GT5678",
    "driver_name": "Jane Smith",
    "vehicle_charges": 1200,
    "labour_charges": 1800,
    "client_contact": "9876543210",
    "created_at": "2025-10-10T05:12:00.448Z",
    "updated_at": "2025-10-10T05:12:00.448Z"
  },
  {
    "id": "449523c7-58d3-4024-a25c-b5e40e26cc59",
    "pickup_id": "PICKUP-20251010-0003",
    "company_name": "XYZ Corporation",
    "lot_number": "LOT-20251010-002",
    "pickup_date": "2025-01-12",
    "status": "pending",
    "vehicle_number": "DL01AB9999",
    "driver_name": "Bob Wilson",
    "vehicle_charges": 2000,
    "labour_charges": 2500,
    "client_contact": "8765432109",
    "created_at": "2025-10-10T05:12:00.450Z",
    "updated_at": "2025-10-10T05:12:00.450Z"
  },
  {
    "id": "a8d970bb-8451-4ef2-8e74-d6a169808ff0",
    "pickup_id": "PICKUP-20251010-0004",
    "company_name": "Test Company",
    "lot_number": "LOT-20251010-003",
    "pickup_date": "2025-01-15",
    "status": "pending",
    "vehicle_number": "TEST123",
    "driver_name": "Test Driver",
    "vehicle_charges": 1000,
    "labour_charges": 1500,
    "client_contact": "1234567890",
    "created_at": "2025-10-10T05:12:22.064Z",
    "updated_at": "2025-10-10T05:12:22.064Z"
  },
  {
    "id": "f890c4d8-6376-4e74-af2b-bb379eb375f2",
    "pickup_id": "PICKUP-20251010-0005",
    "company_name": "Demo Corp",
    "lot_number": "LOT-20251010-004",
    "pickup_date": "2025-01-20",
    "status": "pending",
    "vehicle_number": "DEMO001",
    "driver_name": "Demo Driver",
    "vehicle_charges": 1200,
    "labour_charges": 1800,
    "client_contact": "9876543210",
    "created_at": "2025-10-10T05:20:30.750Z",
    "updated_at": "2025-10-10T05:20:30.750Z"
  },
  {
    "id": "7655aa0c-8740-441f-a083-4d42a75e1aed",
    "pickup_id": "PICKUP-20251010-0006",
    "company_name": "Enhanced Test Corp",
    "lot_number": "LOT-20251010-005",
    "pickup_date": "2025-01-25",
    "status": "pending",
    "vehicle_number": "ENH001",
    "driver_name": "Enhanced Driver",
    "vehicle_charges": 1500,
    "labour_charges": 2000,
    "client_contact": "9876543210",
    "created_at": "2025-10-10T05:33:32.126Z",
    "updated_at": "2025-10-10T05:33:32.126Z"
  }
]